yunpian/__init__.py
yunpian/abc.py
yunpian/core.py
yunpian/sms.py
yunpian/utils.py
yunpian/contrib/__init__.py
yunpian/contrib/aiohttp.py
yunpian-0.1.1.dist-info/DESCRIPTION.rst
yunpian-0.1.1.dist-info/METADATA
yunpian-0.1.1.dist-info/RECORD
yunpian-0.1.1.dist-info/WHEEL
yunpian-0.1.1.dist-info/metadata.json
yunpian-0.1.1.dist-info/top_level.txt
